earthing/__init__.py
earthing-1.1.0.dist-info/LICENSE
earthing-1.1.0.dist-info/METADATA
earthing-1.1.0.dist-info/WHEEL
earthing-1.1.0.dist-info/top_level.txt
earthing-1.1.0.dist-info/RECORD
