Metadata-Version: 2.1
Name: earthing
Version: 1.1.0
Summary: A python library for design of earthing networks in electrical substations.
Home-page: https://github.com/manuvarkey/Earthing
Author: Manu Varkey
Author-email: manuvarkey@gmail.com
Project-URL: Bug Tracker, https://github.com/manuvarkey/Earthing/issues
Keywords: earthing,grounding,electrical
Classifier: Programming Language :: Python :: 3
Classifier: License :: OSI Approved :: GNU General Public License v3 (GPLv3)
Classifier: Operating System :: OS Independent
Classifier: Topic :: Scientific/Engineering
Requires-Python: >=3.6
License-File: LICENSE
Requires-Dist: numpy (>=1.22.0)
Requires-Dist: matplotlib (>=3.5.0)
